flashcard_cli/__init__.py
flashcard_cli/data.py
flashcard_cli/db.py
flashcard_cli/main.py
flashcard_cli/start.py
flashcard_cli/tui.py
flashcard_cli-1.1.0.dist-info/METADATA
flashcard_cli-1.1.0.dist-info/WHEEL
flashcard_cli-1.1.0.dist-info/entry_points.txt
flashcard_cli-1.1.0.dist-info/top_level.txt
flashcard_cli-1.1.0.dist-info/RECORD
