Metadata-Version: 2.4
Name: flashcard-cli
Version: 1.1.0
Summary: A terminal-based flashcard system.
Author-email: 000xs <000xs@users.noreply.github.com>
Project-URL: Homepage, https://github.com/000xs/flashcard-cli
Project-URL: Bug Tracker, https://github.com/000xs/flashcard-cli/issues
Classifier: Programming Language :: Python :: 3
Classifier: License :: OSI Approved :: MIT License
Classifier: Operating System :: OS Independent
Requires-Python: >=3.7
Requires-Dist: typer[all]
Requires-Dist: rich
Requires-Dist: textual
